README.rst
setup.cfg
setup.py
pastebin_python/__init__.py
pastebin_python/pastebin.py
pastebin_python/pastebin_constants.py
pastebin_python/pastebin_exceptions.py
pastebin_python/pastebin_formats.py
pastebin_python/pastebin_options.py
pastebin_python.egg-info/PKG-INFO
pastebin_python.egg-info/SOURCES.txt
pastebin_python.egg-info/dependency_links.txt
pastebin_python.egg-info/top_level.txt