Metadata-Version: 1.1
Name: pastebin-python
Version: 1.2
Summary: A complete pastebin.com API wrapper for Python
Home-page: http://ferdinandsilva.com
Author: Ferdinand Silva
Author-email: ferdinandsilva@ferdinandsilva.com
License: UNKNOWN
Download-URL: https://github.com/six519/PastebinPython
Platform: UNKNOWN
Classifier: Development Status :: 4 - Beta
Classifier: Intended Audience :: Developers
Classifier: Natural Language :: English
Classifier: Programming Language :: Python
Classifier: License :: Freeware
